qmenta/__init__.py
qmenta/anon/__init__.py
qmenta/anon/auto.py
qmenta/anon/dicom.py
qmenta/anon/nifti.py
qmenta/anon/time_utils.py
qmenta_anon-2.1.1.dist-info/METADATA
qmenta_anon-2.1.1.dist-info/WHEEL
qmenta_anon-2.1.1.dist-info/RECORD
