Metadata-Version: 2.3
Name: qmenta-anon
Version: 2.1.1
Summary: The qmenta-anon library is used to anonymize files before transferring them to the QMENTA platform.
Author: QMENTA
Author-email: dev@qmenta.com
Requires-Python: >=3.10,<4.0
Classifier: Development Status :: 4 - Beta
Classifier: Intended Audience :: Developers
Classifier: License :: Other/Proprietary License
Classifier: Programming Language :: Python :: 3
Classifier: Programming Language :: Python :: 3.10
Classifier: Programming Language :: Python :: 3.11
Classifier: Programming Language :: Python :: 3.12
Classifier: Programming Language :: Python :: 3.13
Classifier: Topic :: Scientific/Engineering :: Medical Science Apps.
Requires-Dist: coverage[toml] (>=7.3.0,<8.0.0)
Requires-Dist: nibabel (>=5.3.2,<6.0.0)
Requires-Dist: numpy (<2.0)
Requires-Dist: pydicom (>=2.3.0,<3.0.0)
Requires-Dist: pytest (>=7.4.0,<8.0.0)
Requires-Dist: pytest-cov (>=6.1.1,<7.0.0)
Requires-Dist: setuptools (>=80.3.1,<81.0.0)
